qsl/__init__.py
qsl/app.py
qsl/cli.py
qsl/common.py
qsl/files.py
qsl/version.py
qsl/widgets.py
qsl/testing/__init__.py
qsl/testing/files.py
qsl/testing/data/README.md
qsl/testing/data/image1.jpg
qsl/testing/data/image10.jpg
qsl/testing/data/image2.jpg
qsl/testing/data/image3.45ccw.jpg
qsl/testing/data/image3.jpg
qsl/testing/data/image4.jpg
qsl/testing/data/image5.jpg
qsl/testing/data/image6.jpg
qsl/testing/data/image7.jpg
qsl/testing/data/image8.jpg
qsl/testing/data/image9.jpg
qsl/testing/data/video1.m4v
qsl/testing/data/video2.m4v
qslwidgets/dist/anywidget/index.css
qslwidgets/dist/anywidget/index.js
qslwidgets/dist/browser/index.css
qslwidgets/dist/browser/index.js
qslwidgets/dist/eel/index.css
qslwidgets/dist/eel/index.html
qslwidgets/dist/eel/index.js
qslwidgets/dist/svelte/anywidget.d.ts
qslwidgets/dist/svelte/anywidget.js
qslwidgets/dist/svelte/browser.d.ts
qslwidgets/dist/svelte/browser.js
qslwidgets/dist/svelte/eel.d.ts
qslwidgets/dist/svelte/eel.html
qslwidgets/dist/svelte/eel.js
qslwidgets/dist/svelte/widget.d.ts
qslwidgets/dist/svelte/widget.js
qslwidgets/dist/svelte/components/BatchImageItem.svelte
qslwidgets/dist/svelte/components/BatchImageItem.svelte.d.ts
qslwidgets/dist/svelte/components/BatchImageLabeler.svelte
qslwidgets/dist/svelte/components/BatchImageLabeler.svelte.d.ts
qslwidgets/dist/svelte/components/Button.svelte
qslwidgets/dist/svelte/components/Button.svelte.d.ts
qslwidgets/dist/svelte/components/ButtonGroup.svelte
qslwidgets/dist/svelte/components/ButtonGroup.svelte.d.ts
qslwidgets/dist/svelte/components/ClickTarget.svelte
qslwidgets/dist/svelte/components/ClickTarget.svelte.d.ts
qslwidgets/dist/svelte/components/ConfigEditor.svelte
qslwidgets/dist/svelte/components/ConfigEditor.svelte.d.ts
qslwidgets/dist/svelte/components/ControlMenu.svelte
qslwidgets/dist/svelte/components/ControlMenu.svelte.d.ts
qslwidgets/dist/svelte/components/EnhancementControls.svelte
qslwidgets/dist/svelte/components/EnhancementControls.svelte.d.ts
qsl-0.2.47.dist-info/METADATA
qsl-0.2.47.dist-info/WHEEL
qsl-0.2.47.dist-info/entry_points.txt
qsl-0.2.47.dist-info/licenses/LICENSE
qsl-0.2.47.dist-info/RECORD
