Metadata-Version: 2.4
Name: qsl
Version: 0.2.47
Summary: A package for labeling image, video, and time series data quickly
Project-URL: Homepage, https://github.com/faustomorales/qsl
Project-URL: Repository, https://github.com/faustomorales/qsl
Author-email: Fausto Morales <fausto@robinbay.com>
License-Expression: MIT
License-File: LICENSE
Keywords: IPython,Jupyter,Widgets
Classifier: Operating System :: MacOS
Classifier: Operating System :: Microsoft :: Windows
Classifier: Operating System :: POSIX :: Linux
Classifier: Operating System :: Unix
Classifier: Programming Language :: Python :: 3
Classifier: Programming Language :: Python :: 3 :: Only
Requires-Python: >=3.8
Requires-Dist: anywidget>=0.9.18
Requires-Dist: click
Requires-Dist: eel
Requires-Dist: filetype
Requires-Dist: ipywidgets>=7.0.0
Requires-Dist: opencv-python-headless
Provides-Extra: app
Requires-Dist: click; extra == 'app'
Requires-Dist: eel>=0.18.2; extra == 'app'
